cookie_alert/__init__.py
cookie_alert/admin.py
cookie_alert/app_settings.py
cookie_alert/apps.py
cookie_alert/models.py
cookie_alert/test_settings.py
cookie_alert/test_urls.py
cookie_alert/views.py
cookie_alert/locale/de/LC_MESSAGES/django.mo
cookie_alert/locale/de/LC_MESSAGES/django.po
cookie_alert/static/cookie_alert/css/cookie_alert.css
cookie_alert/static/cookie_alert/js/cookie_alert.js
cookie_alert/templates/cookie_alert/_cookie_includes.html
cookie_alert/templates/cookie_alert/base.html
cookie_alert/templates/cookie_alert/footer.html
cookie_alert/templates/cookie_alert/inline_header.html
cookie_alert/templates/cookie_alert/modal.html
cookie_alert/templates/cookie_alert/top_header.html
cookie_alert/templatetags/cookie_alert.py
cookie_alert/tests/__init__.py
cookie_alert/tests/test_cookies.py
django_cookie_alert-0.1.16.dist-info/LICENSE
django_cookie_alert-0.1.16.dist-info/METADATA
django_cookie_alert-0.1.16.dist-info/WHEEL
django_cookie_alert-0.1.16.dist-info/top_level.txt
django_cookie_alert-0.1.16.dist-info/RECORD
